ModuleHandler/__init__.py
ModuleHandler/module_config.py
ModuleHandler/registry.py
ModuleHandler/tools.py
modulehandler-0.5.dist-info/LICENSE
modulehandler-0.5.dist-info/METADATA
modulehandler-0.5.dist-info/WHEEL
modulehandler-0.5.dist-info/top_level.txt
modulehandler-0.5.dist-info/RECORD
