Metadata-Version: 2.1
Name: modulehandler
Version: 0.5
Summary: A dynamic module handler, with standalone tools
Home-page: https://github.com/divad1196/ModuleHandler
Author: Gallay David
Author-email: davidtennis96@hotmail.com
License: UNKNOWN
Platform: UNKNOWN
Classifier: Programming Language :: Python :: 3
Classifier: License :: OSI Approved :: MIT License
Classifier: Operating System :: OS Independent
Requires-Dist: markdown
Requires-Dist: pydantic
Requires-Dist: typing
